MANIFEST.in
README.txt
setup.py
ICHT_PatientExperience/__init__.py
ICHT_PatientExperience/pred.py
ICHT_PatientExperience.egg-info/PKG-INFO
ICHT_PatientExperience.egg-info/SOURCES.txt
ICHT_PatientExperience.egg-info/dependency_links.txt
ICHT_PatientExperience.egg-info/top_level.txt
ICHT_PatientExperience/models/Q1Senti.pkl
ICHT_PatientExperience/models/Q1Topic.pkl
ICHT_PatientExperience/models/Q2Senti.pkl
ICHT_PatientExperience/models/Q2Topic.pkl
ICHT_PatientExperience/models/feature11.pkl
ICHT_PatientExperience/models/feature12.pkl
ICHT_PatientExperience/models/feature21.pkl
ICHT_PatientExperience/models/feature22.pkl
ICHT_PatientExperience/models/tfidftransformer11.pkl
ICHT_PatientExperience/models/tfidftransformer12.pkl
ICHT_PatientExperience/models/tfidftransformer21.pkl
ICHT_PatientExperience/models/tfidftransformer22.pkl