Metadata-Version: 1.0
Name: ICHT_PatientExperience
Version: 2.5
Summary: A pre-trained text classification model
Home-page: https://github.com/ykevingrox/ICHT_PatientExperience
Author: Jingxian You
Author-email: jingxian.you@nhs.net
License: UNKNOWN
Platform: UNKNOWN
